<MenuBar>
	<Menu name="DefJam">
		<Menu name="About DefJam" shell="win -a"/>
		<Menu type="divider"/>
		<Menu name="Quit DefJam" shell="win -c"/>
	</Menu>
	<Menu name="File">
		<Menu name="Open&#8230;" disabled="1"/>
		<Menu type="divider"/>
		<Menu name="Save" disabled="1"/>
		<Menu name="Save As&#8230;" disabled="1"/>
		<Menu type="divider"/>
		<Menu name="Close file" click="close-file"/>
	</Menu>
	<Menu name="Help">
		<Menu name="Help" click="open-help"/>
		<Menu type="divider"/>
		<Menu name="Source Code"/>
	</Menu>

	<Menu for="track-title-menu">
		<Menu name="Rename Track"/>
		<Menu type="divider"/>
		<Menu type="colors" caption="Track Color:" break="9">
			<Color arg="#48c" active="1"/>
			<Color arg="#77c"/>
			<Color arg="#96a"/>
			<Color arg="#69b"/>
			<Color arg="#b66"/>
			<Color arg="#494"/>
			<Color arg="#09f"/>
			<Color arg="#c70"/>
			<Color arg="#0bc"/>

			<Color arg="#19a"/>
			<Color arg="#d66"/>
			<Color arg="#a75135"/>
			<Color arg="#815f52"/>
			<Color arg="#ae9a23"/>
			<Color arg="#569e38"/>
			<Color arg="#1c9b8e"/>
			<Color arg="#377392"/>
			<Color arg="#4367b6"/>

			<Color arg="#715bbe"/>
			<Color arg="#b45dbe"/>
			<Color arg="#c17ea1"/>
			<Color arg="#ed9368"/>
			<Color arg="#e3569f"/>
			<Color arg="#98724e"/>
			<Color arg="#5c5c5c"/>
			<Color arg="#a9a9a9"/>
			<Color arg="#7b7b7b"/>
		</Menu>
		<Menu type="divider"/>
		<Menu name="Delete Track"/>
	</Menu>

	<Menu for="display-menu">
		<Menu name="Show Bar / Beat" click="show-display" arg="bar-beat" check-group="display-view" is-checked="1"/>
		<Menu name="Show Time" click="show-display" arg="time" check-group="display-view"/>
	</Menu>
</MenuBar>